fpmul.v
module fpmul(
input clk,in_ready,
input [10:0] a,b,
output reg [10:0]product,
output reg done
);

reg sign_a,sign_b,sign_p;
reg [5:0] exp_a,exp_b,exp_p;
reg [3:0] man_a,man_b,man_p;
reg [5:0] temp_expa,temp_expb,temp_expp;
reg [4:0] temp_mana,temp_manb;
reg [9:0]temp_manp;

always@(posedge clk) begin
if(a==0||b==0)begin
product=0;
done=1'b1;
end
else begin
if(in_ready)begin
{sign_a,exp_a,man_a}<=a;
{sign_b,exp_b,man_b}<=b;
temp_mana={1'b1,man_a};
temp_manb={1'b1,man_b};
temp_expa=exp_a-6'd31;
temp_expb=exp_b-6'd31;

sign_p=sign_a^sign_b;
temp_expp = temp_expa+temp_expb;
temp_manp = temp_mana*temp_manb;
if(temp_manp[9]) begin
man_p=temp_manp[8:5];
exp_p=temp_expp+6'd32;
product={sign_p,exp_p,man_p};
done=1'b1;
end
else if(temp_manp[9]==0)begin
man_p=temp_manp[7:4];
exp_p=temp_expp+6'd31;
product={sign_p,exp_p,man_p};
done=1'b1;
end
end
end
end
endmodule

fpmul_tb.v
`timescale 1ns/1ps
module fpmul_tb;
reg clk=1'b0;
reg in_ready;
reg [10:0] a,b;
wire [10:0] product;
wire done;

fpmul uut(.clk(clk),.in_ready(in_ready),.a(a),.b(b),.product(product),.done(done));

always clk = #5 ~clk;

initial begin
$dumpfile("fpmul.vcd");
$dumpvars(0,fpmul_tb);

in_ready=1'b1;
a=11'b1001_1111_000;
b=11'b0000_0101_110;

#50

a=11'b0010_0101_011;
b=11'b1010_1010_110;

#50

a=11'b1010_1111_110;
b=11'b1100_1011_010;
#200

$finish;
end
endmodule

fpmul.vcd
$date
	Wed Oct 25 14:51:28 2023
$end
$version
	Icarus Verilog
$end
$timescale
	1ps
$end
$scope module fpmul_tb $end
$var wire 11 ! product [10:0] $end
$var wire 1 " done $end
$var reg 11 # a [10:0] $end
$var reg 11 $ b [10:0] $end
$var reg 1 % clk $end
$var reg 1 & in_ready $end
$scope module uut $end
$var wire 11 ' a [10:0] $end
$var wire 11 ( b [10:0] $end
$var wire 1 % clk $end
$var wire 1 & in_ready $end
$var reg 1 " done $end
$var reg 6 ) exp_a [5:0] $end
$var reg 6 * exp_b [5:0] $end
$var reg 6 + exp_p [5:0] $end
$var reg 4 , man_a [3:0] $end
$var reg 4 - man_b [3:0] $end
$var reg 4 . man_p [3:0] $end
$var reg 11 / product [10:0] $end
$var reg 1 0 sign_a $end
$var reg 1 1 sign_b $end
$var reg 1 2 sign_p $end
$var reg 6 3 temp_expa [5:0] $end
$var reg 6 4 temp_expb [5:0] $end
$var reg 6 5 temp_expp [5:0] $end
$var reg 5 6 temp_mana [4:0] $end
$var reg 5 7 temp_manb [4:0] $end
$var reg 10 8 temp_manp [9:0] $end
$upscope $end
$upscope $end
$enddefinitions $end
#0
$dumpvars
bx 8
bx 7
bx 6
bx 5
bx 4
bx 3
x2
x1
x0
bx /
bx .
bx -
bx ,
bx +
bx *
bx )
b101110 (
b10011111000 '
1&
0%
b101110 $
b10011111000 #
x"
bx !
$end
#5000
01
b10 *
b1110 -
10
b1111 )
b1000 ,
b1xxxx 7
b1xxxx 6
1%
#10000
0%
#15000
1"
b11100110110 !
b11100110110 /
b110011 +
b110 .
b1011010000 8
b10011 5
12
b100011 4
b110000 3
b11110 7
b11000 6
1%
#20000
0%
#25000
1%
#30000
0%
#35000
1%
#40000
0%
#45000
1%
#50000
0%
b10101010110 $
b10101010110 (
b100101011 #
b100101011 '
#55000
11
b10101 *
b110 -
00
b10010 )
b1011 ,
1%
#60000
0%
#65000
b10010010010 !
b10010010010 /
b1001 +
b10 .
b1001010010 8
b101001 5
b110110 4
b110011 3
b10110 7
b11011 6
1%
#70000
0%
#75000
1%
#80000
0%
#85000
1%
#90000
0%
#95000
1%
#100000
0%
b11001011010 $
b11001011010 (
b10101111110 #
b10101111110 '
#105000
b100101 *
b1010 -
10
b10111 )
b1110 ,
1%
#110000
0%
#115000
b111101000 !
b111101000 /
b11110 +
b1000 .
b1100001100 8
b111110 5
02
b110 4
b111000 3
b11010 7
b11110 6
1%
